Workbook

Sheet Instructions
B2: 🧾 HUSTLE MATH · free side-hustle calculator
B3: By Side Hustle Receipts · Real costs. Real hours. Real payouts. · Version Oct 2026 (re-check rates every January and July)
B5: WHAT THIS IS | C5: A free calculator that turns 'I made $25/hr' into what you actually keep per hour after car costs, platform fees, other expenses and self-employment tax.
B6: HOW TO USE | C6: 1) Go to File → Make a copy (this file is view-only for everyone else). 2) Type ONLY in YELLOW cells. 3) GREEN cells are formulas — don't type over them. 4) Replace every row marked EXAMPLE with your own numbers, or clear it.
B7: COLOR KEY | C7: YELLOW = your input · GREEN = calculated result · ORANGE text 'EXAMPLE' = sample data so you can see how it works (not a statistic, not a promise).
B8: TAB: Hourly Pay Calculator | C8: One shift / one gig / one week at a time. Enter gross pay, ALL hours (waiting, driving, admin, pitching count), miles, and expenses. Shows your true hourly pay.
B9: TAB: Side Hustle Comparison | C9: Up to 10 hustles side by side, ranked automatically by true hourly pay. Uses the same mileage rate and tax settings as the calculator.
B10: TAB: Digital Product Fee Calculator | C10: What Etsy, Gumroad and Payhip leave you from one digital sale (and from N sales). Fee rates live in yellow cells with sources, so you can update them when platforms change.
B11: TAB: Monthly Tracker | C11: Log every session. Totals, true hourly per hustle and a tax set-aside estimate update automatically.
B12: THE FORMULA | C12: Net profit = Gross − (Miles × $/mile) − Fees − Other expenses. SE tax = Net × 92.35% × 15.3% (if net > 0). True hourly = (Net − SE tax − optional income tax) ÷ Hours.
B13: MILEAGE RATE | C13: Default 76¢/mile = IRS business standard mileage rate for July 1–Dec 31, 2026 (it was 72.5¢ Jan 1–Jun 30, 2026). It is the IRS's all-in estimate (fuel, maintenance, depreciation, insurance). Source: https://www.irs.gov/tax-professionals/standard-mileage-rates . For 'cash out of pocket only', AAA's 2026 study puts fuel (17.32¢) + maintenance/repair/tires (11.73¢) ≈ 29¢/mile: https://newsroom.aaa.com/wp-content/uploads/2026/09/AAA_YDC-Fact-Sheet_2026.pdf
B14: SELF-EMPLOYMENT TAX | C14: 15.3% (12.4% Social Security + 2.9% Medicare) on 92.35% of net SE earnings; generally owed if net SE earnings are $400+ for the year. Half is deductible for income tax. Source: IRS Topic 554 https://www.irs.gov/taxtopics/tc554 . The calculator applies SE tax per session as an approximation of your annual bill.
B15: INCOME TAX | C15: Optional cell, default 0%. Your federal/state income tax rate depends on your whole return, so this sheet does not guess it. If you add a rate, it is applied to net profit minus half the SE tax (a simplification).
B16: FEE SOURCES | C16: Etsy: $0.20 listing + 6.5% transaction https://www.etsy.com/legal/fees/ ; US payment processing 3% + $0.25 https://help.etsy.com/hc/en-us/articles/115015628847 ; Offsite Ads 12–15% if a sale comes from Etsy's ads. Gumroad: 10% + $0.50 direct, plus card processing 2.9% + $0.30; Discover marketplace sales flat 30% https://gumroad.com/help/article/66-gumroads-fees . Payhip: Free plan 5% transaction fee + PayPal/Stripe processing https://payhip.com/pricing ; Stripe US cards 2.9% + 30¢ https://stripe.com/pricing .
... B18: DISCLAIMER | C18: Educational tool only. Not tax, legal or financial advice. Rates and platform fees change — verify on the linked pages before relying on a number. Talk to a qualified tax professional about your situation.

Sheet Hourly Pay Calculator
B2: HOURLY PAY CALCULATOR · what you actually keep
B3: Type in YELLOW cells only. Pre-filled values are an EXAMPLE (1 delivery hour, $25 gross, 14 miles) — replace them with your own.
B5: INPUT | C5: VALUE | D5: NOTES / SOURCE
B6: Gross pay (incl. tips & bonuses) | C6: 25 | D6: EXAMPLE value. Everything the platform/client paid you for this period.
B7: Hours worked (ALL of them) | C7: 1 | D7: EXAMPLE value. Include waiting, driving to the zone, pitching, admin, packing.
B8: Miles driven for this work | C8: 14 | D8: EXAMPLE value. Use your mileage log (odometer or app).
B9: Mileage cost per mile ($) | C9: 0.76 | D9: Default = IRS business standard mileage rate, Jul 1–Dec 31, 2026 (76¢). https://www.irs.gov/tax-professionals/standard-mileage-rates · Cash-only alternative ≈ $0.29 (AAA 2026 fuel 17.32¢ + maintenance 11.73¢).
B10: Platform fees NOT already taken out | C10: 0 | D10: Leave 0 if the app pays you net of its cut.
B11: Other expenses (supplies, parking, phone share…) | C11: 0 | D11: EXAMPLE value. Only costs caused by this work.
B12: Self-employment tax rate | C12: 0.153 | D12: 15.3% = 12.4% Social Security + 2.9% Medicare. IRS Topic 554: https://www.irs.gov/taxtopics/tc554
B13: Share of net subject to SE tax | C13: 0.9235 | D13: 92.35% of net SE earnings (IRS Topic 554).
B14: Optional: income tax rate (your estimate) | C14: 0 | D14: Default 0% (not included). Depends on your whole tax return.
B16: RESULT | C16: VALUE | D16: HOW IT'S CALCULATED
B17: Car cost | C17: =C8*C9 | D17: Miles × $/mile
B18: Total expenses | C18: =C17+C10+C11 | D18: Car + fees + other
B19: Net profit before tax | C19: =C6-C18 | D19: Gross − expenses
B20: Self-employment tax (approx.) | C20: =MAX(0,C19)*C13*C12 | D20: Net × 92.35% × 15.3%
B21: Income tax (optional) | C21: =MAX(0,C19-C20/2)*C14 | D21: (Net − ½ SE tax) × your rate
B22: Take-home | C22: =C19-C20-C21 | D22: Net − taxes
B23: Advertised hourly (gross ÷ hours) | C23: =IF(C7>0,C6/C7,"") | D23: What the app/listing implies
B24: TRUE HOURLY PAY | C24: =IF(C7>0,C22/C7,"") | D24: Take-home ÷ ALL hours
B25: % of advertised pay you keep | C25: =IF(C6>0,C22/C6,"") | D25: Take-home ÷ gross
B27: Check: with the EXAMPLE inputs this should show ≈ $12.33 true hourly (matches the Side Hustle Receipts post). Not tax advice; SE tax is generally owed only if your yearly net SE earnings are $400+.

Sheet Side Hustle Comparison
B2: SIDE HUSTLE COMPARISON · ranked by true hourly pay
B3: Up to 10 hustles. Enter one typical week (or one typical gig) per row. $/mile defaults to the calculator's rate; SE tax uses the calculator's settings. Rows 6–9 are EXAMPLE data (labeled) — overwrite or clear them.
B5: Hustle | C5: Gross pay | D5: Hours | E5: Miles | F5: $/mile | G5: Fees not yet deducted | H5: Other expenses | I5: Net profit | J5: SE tax | K5: Take-home | L5: TRUE HOURLY | M5: Rank | O5: helper (ignore)
B6: EXAMPLE: Food delivery (1 wk) | C6: 146.6 | D6: 10 | E6: 130 | F6: ='Hourly Pay Calculator'!$C$9 | G6: 0 | H6: 0 | I6: =IF(B6="","",C6-E6*F6-G6-H6) | J6: =IF(B6="","",MAX(0,I6)*'Hourly Pay Calculator'!$C$13*'Hourly Pay Calculator'!$C$12) | K6: =IF(B6="","",I6-J6) | L6: =IF(OR(B6="",N(D6)<=0),"",K6/D6) | M6: =IF(L6="","",RANK(L6,$L$6:$L$15,0)) | O6: =IF(L6="","",L6-ROW()/1000000000)
B7: EXAMPLE: Tutoring on a platform (1 wk) | C7: 160 | D7: 5 | E7: 0 | F7: ='Hourly Pay Calculator'!$C$9 | G7: 40 | H7: 0 | I7: =IF(B7="","",C7-E7*F7-G7-H7) | J7: =IF(B7="","",MAX(0,I7)*'Hourly Pay Calculator'!$C$13*'Hourly Pay Calculator'!$C$12) | K7: =IF(B7="","",I7-J7) | L7: =IF(OR(B7="",N(D7)<=0),"",K7/D7) | M7: =IF(L7="","",RANK(L7,$L$6:$L$15,0)) | O7: =IF(L7="","",L7-ROW()/1000000000)
B8: EXAMPLE: Dog walking app (1 wk) | C8: 125 | D8: 3.75 | E8: 20 | F8: ='Hourly Pay Calculator'!$C$9 | G8: 25 | H8: 0 | I8: =IF(B8="","",C8-E8*F8-G8-H8) | J8: =IF(B8="","",MAX(0,I8)*'Hourly Pay Calculator'!$C$13*'Hourly Pay Calculator'!$C$12) | K8: =IF(B8="","",I8-J8) | L8: =IF(OR(B8="",N(D8)<=0),"",K8/D8) | M8: =IF(L8="","",RANK(L8,$L$6:$L$15,0)) | O8: =IF(L8="","",L8-ROW()/1000000000)
B9: EXAMPLE: Etsy templates (month 1) | C9: 120 | D9: 20 | E9: 0 | F9: ='Hourly Pay Calculator'!$C$9 | G9: 15.9 | H9: 0 | I9: =IF(B9="","",C9-E9*F9-G9-H9) | J9: =IF(B9="","",MAX(0,I9)*'Hourly Pay Calculator'!$C$13*'Hourly Pay Calculator'!$C$12) | K9: =IF(B9="","",I9-J9) | L9: =IF(OR(B9="",N(D9)<=0),"",K9/D9) | M9: =IF(L9="","",RANK(L9,$L$6:$L$15,0)) | O9: =IF(L9="","",L9-ROW()/1000000000)
F10: ='Hourly Pay Calculator'!$C$9 | I10: =IF(B10="","",C10-E10*F10-G10-H10) | J10: =IF(B10="","",MAX(0,I10)*'Hourly Pay Calculator'!$C$13*'Hourly Pay Calculator'!$C$12) | K10: =IF(B10="","",I10-J10) | L10: =IF(OR(B10="",N(D10)<=0),"",K10/D10) | M10: =IF(L10="","",RANK(L10,$L$6:$L$15,0)) | O10: =IF(L10="","",L10-ROW()/1000000000)
F11: ='Hourly Pay Calculator'!$C$9 | I11: =IF(B11="","",C11-E11*F11-G11-H11) | J11: =IF(B11="","",MAX(0,I11)*'Hourly Pay Calculator'!$C$13*'Hourly Pay Calculator'!$C$12) | K11: =IF(B11="","",I11-J11) | L11: =IF(OR(B11="",N(D11)<=0),"",K11/D11) | M11: =IF(L11="","",RANK(L11,$L$6:$L$15,0)) | O11: =IF(L11="","",L11-ROW()/1000000000)
F12: ='Hourly Pay Calculator'!$C$9 | I12: =IF(B12="","",C12-E12*F12-G12-H12) | J12: =IF(B12="","",MAX(0,I12)*'Hourly Pay Calculator'!$C$13*'Hourly Pay Calculator'!$C$12) | K12: =IF(B12="","",I12-J12) | L12: =IF(OR(B12="",N(D12)<=0),"",K12/D12) | M12: =IF(L12="","",RANK(L12,$L$6:$L$15,0)) | O12: =IF(L12="","",L12-ROW()/1000000000)
F13: ='Hourly Pay Calculator'!$C$9 | I13: =IF(B13="","",C13-E13*F13-G13-H13) | J13: =IF(B13="","",MAX(0,I13)*'Hourly Pay Calculator'!$C$13*'Hourly Pay Calculator'!$C$12) | K13: =IF(B13="","",I13-J13) | L13: =IF(OR(B13="",N(D13)<=0),"",K13/D13) | M13: =IF(L13="","",RANK(L13,$L$6:$L$15,0)) | O13: =IF(L13="","",L13-ROW()/1000000000)
F14: ='Hourly Pay Calculator'!$C$9 | I14: =IF(B14="","",C14-E14*F14-G14-H14) | J14: =IF(B14="","",MAX(0,I14)*'Hourly Pay Calculator'!$C$13*'Hourly Pay Calculator'!$C$12) | K14: =IF(B14="","",I14-J14) | L14: =IF(OR(B14="",N(D14)<=0),"",K14/D14) | M14: =IF(L14="","",RANK(L14,$L$6:$L$15,0)) | O14: =IF(L14="","",L14-ROW()/1000000000)
F15: ='Hourly Pay Calculator'!$C$9 | I15: =IF(B15="","",C15-E15*F15-G15-H15) | J15: =IF(B15="","",MAX(0,I15)*'Hourly Pay Calculator'!$C$13*'Hourly Pay Calculator'!$C$12) | K15: =IF(B15="","",I15-J15) | L15: =IF(OR(B15="",N(D15)<=0),"",K15/D15) | M15: =IF(L15="","",RANK(L15,$L$6:$L$15,0)) | O15: =IF(L15="","",L15-ROW()/1000000000)
B17: Notes: EXAMPLE rows are illustrations built from the ebook's worked examples (food delivery gross ≈ Gridwise 2025 avg $14.66/hr × 10 hrs; 13 mi/hr is an assumption). Fees column = platform cut not already removed. Not tax advice.
B20: LEADERBOARD (auto-sorted)
B21: # | C21: Hustle | D21: True hourly
B22: 1 | C22: =IFERROR(INDEX($B$6:$B$15,MATCH(LARGE($O$6:$O$15,1),$O$6:$O$15,0)),"") | D22: =IFERROR(INDEX($L$6:$L$15,MATCH(LARGE($O$6:$O$15,1),$O$6:$O$15,0)),"")
B23: 2 | C23: =IFERROR(INDEX($B$6:$B$15,MATCH(LARGE($O$6:$O$15,2),$O$6:$O$15,0)),"") | D23: =IFERROR(INDEX($L$6:$L$15,MATCH(LARGE($O$6:$O$15,2),$O$6:$O$15,0)),"")
B24: 3 | C24: =IFERROR(INDEX($B$6:$B$15,MATCH(LARGE($O$6:$O$15,3),$O$6:$O$15,0)),"") | D24: =IFERROR(INDEX($L$6:$L$15,MATCH(LARGE($O$6:$O$15,3),$O$6:$O$15,0)),"")
B25: 4 | C25: =IFERROR(INDEX($B$6:$B$15,MATCH(LARGE($O$6:$O$15,4),$O$6:$O$15,0)),"") | D25: =IFERROR(INDEX($L$6:$L$15,MATCH(LARGE($O$6:$O$15,4),$O$6:$O$15,0)),"")
B26: 5 | C26: =IFERROR(INDEX($B$6:$B$15,MATCH(LARGE($O$6:$O$15,5),$O$6:$O$15,0)),"") | D26: =IFERROR(INDEX($L$6:$L$15,MATCH(LARGE($O$6:$O$15,5),$O$6:$O$15,0)),"")
B27: 6 | C27: =IFERROR(INDEX($B$6:$B$15,MATCH(LARGE($O$6:$O$15,6),$O$6:$O$15,0)),"") | D27: =IFERROR(INDEX($L$6:$L$15,MATCH(LARGE($O$6:$O$15,6),$O$6:$O$15,0)),"")
B28: 7 | C28: =IFERROR(INDEX($B$6:$B$15,MATCH(LARGE($O$6:$O$15,7),$O$6:$O$15,0)),"") | D28: =IFERROR(INDEX($L$6:$L$15,MATCH(LARGE($O$6:$O$15,7),$O$6:$O$15,0)),"")
B29: 8 | C29: =IFERROR(INDEX($B$6:$B$15,MATCH(LARGE($O$6:$O$15,8),$O$6:$O$15,0)),"") | D29: =IFERROR(INDEX($L$6:$L$15,MATCH(LARGE($O$6:$O$15,8),$O$6:$O$15,0)),"")
B30: 9 | C30: =IFERROR(INDEX($B$6:$B$15,MATCH(LARGE($O$6:$O$15,9),$O$6:$O$15,0)),"") | D30: =IFERROR(INDEX($L$6:$L$15,MATCH(LARGE($O$6:$O$15,9),$O$6:$O$15,0)),"")
B31: 10 | C31: =IFERROR(INDEX($B$6:$B$15,MATCH(LARGE($O$6:$O$15,10),$O$6:$O$15,0)),"") | D31: =IFERROR(INDEX($L$6:$L$15,MATCH(LARGE($O$6:$O$15,10),$O$6:$O$15,0)),"")

Sheet Digital Product Fee Calculator
B2: DIGITAL PRODUCT FEE CALCULATOR · Etsy vs Gumroad vs Payhip
B3: Yellow = inputs and fee rates (update when platforms change their fees). Pre-filled price is an EXAMPLE.
B5: YOUR SALE | C5: VALUE | G5: NOTES
B6: Product price ($) | C6: 12 | G6: EXAMPLE price.
B7: Number of sales (for totals) | C7: 10 | G7: EXAMPLE count.
B8: Sales tax collected on the order ($) | C8: 0 | G8: Etsy's processing fee is charged on the total incl. tax. Leave 0 if unsure.
B9: Etsy: sale came from Offsite Ads? (rate) | C9: 0 | G9: 0% normally; 15% (or 12% for shops over $10k/yr) when Etsy's Offsite Ads drove the sale. Etsy Fees & Payments Policy.
B10: Gumroad: sale came via Discover marketplace? (1=yes, 0=no) | C10: 0 | G10: Discover sales are a flat 30% incl. processing (Gumroad help).
B12: FEE RATES (edit if they change) | C12: Etsy | D12: Gumroad | E12: Payhip (Free) | G12: SOURCE
B13: Listing fee per sale ($) | C13: 0.2 | D13: 0 | E13: 0 | G13: Etsy $0.20 per listing (renews after each sale): https://www.etsy.com/legal/fees/
B14: Platform % fee | C14: 0.065 | D14: 0.1 | E14: 0.05 | G14: Etsy 6.5% transaction fee · Gumroad 10% (direct) https://gumroad.com/help/article/66-gumroads-fees · Payhip Free plan 5% https://payhip.com/pricing
B15: Platform flat fee per sale ($) | C15: 0 | D15: 0.5 | E15: 0 | G15: Gumroad $0.50 per sale
B16: Payment processing % | C16: 0.03 | D16: 0.029 | E16: 0.029 | G16: Etsy US 3% https://help.etsy.com/hc/en-us/articles/115015628847 · Gumroad card 2.9% · Payhip passes Stripe/PayPal standard rates; Stripe US cards 2.9% https://stripe.com/pricing
B17: Payment processing flat ($) | C17: 0.25 | D17: 0.3 | E17: 0.3 | G17: Etsy $0.25 · Gumroad card $0.30 · Stripe 30¢
B18: Marketplace (Discover) all-in rate | C18: 0 | D18: 0.3 | E18: 0 | G18: Gumroad Discover: flat 30%
B20: RESULT PER SALE | C20: Etsy | D20: Gumroad | E20: Payhip (Free) | G20: HOW
B21: Total fees per sale | C21: =C13+C14*C6+C9*C6+C16*(C6+C8)+C17 | D21: =IF(C10=1,D18*C6,D14*C6+D15+D16*C6+D17) | E21: =E13+E14*C6+E15+E16*C6+E17 | G21: Etsy: listing + 6.5% + Offsite Ads (if any) + 3% of (price+tax) + $0.25 · Gumroad: 10% + $0.50 + 2.9% + $0.30 (or 30% Discover) · Payhip: 5% + 2.9% + $0.30
B22: You keep per sale | C22: =C6-C21 | D22: =C6-D21 | E22: =C6-E21 | G22: Price − fees (before income/SE tax)
B23: Fees as % of price | C23: =IF($C$6>0,C21/$C$6,"") | D23: =IF($C$6>0,D21/$C$6,"") | E23: =IF($C$6>0,E21/$C$6,"") | G23: Flat fees hurt cheap products most
B24: You keep from N sales | C24: =C22*$C$7 | D24: =D22*$C$7 | E24: =E22*$C$7 | G24: Per-sale keep × number of sales
B25: Self-employment tax on that (approx.) | C25: =MAX(0,C24)*'Hourly Pay Calculator'!$C$13*'Hourly Pay Calculator'!$C$12 | D25: =MAX(0,D24)*'Hourly Pay Calculator'!$C$13*'Hourly Pay Calculator'!$C$12 | E25: =MAX(0,E24)*'Hourly Pay Calculator'!$C$13*'Hourly Pay Calculator'!$C$12 | G25: Uses calculator SE settings; ignores other business costs
B27: PRICE LADDER · what each price nets you (direct sales, no ads, no tax)
B28: Price (edit) | C28: Etsy keeps you | D28: Gumroad keeps you | E28: Payhip keeps you
B29: 5 | C29: =B29-($C$13+$C$14*B29+$C$16*B29+$C$17) | D29: =B29-($D$14*B29+$D$15+$D$16*B29+$D$17) | E29: =B29-($E$13+$E$14*B29+$E$15+$E$16*B29+$E$17)
B30: 9 | C30: =B30-($C$13+$C$14*B30+$C$16*B30+$C$17) | D30: =B30-($D$14*B30+$D$15+$D$16*B30+$D$17) | E30: =B30-($E$13+$E$14*B30+$E$15+$E$16*B30+$E$17)
B31: 12 | C31: =B31-($C$13+$C$14*B31+$C$16*B31+$C$17) | D31: =B31-($D$14*B31+$D$15+$D$16*B31+$D$17) | E31: =B31-($E$13+$E$14*B31+$E$15+$E$16*B31+$E$17)
B32: 19 | C32: =B32-($C$13+$C$14*B32+$C$16*B32+$C$17) | D32: =B32-($D$14*B32+$D$15+$D$16*B32+$D$17) | E32: =B32-($E$13+$E$14*B32+$E$15+$E$16*B32+$E$17)
B33: 29 | C33: =B33-($C$13+$C$14*B33+$C$16*B33+$C$17) | D33: =B33-($D$14*B33+$D$15+$D$16*B33+$D$17) | E33: =B33-($E$13+$E$14*B33+$E$15+$E$16*B33+$E$17)
B35: Excludes: sales tax, currency conversion, Etsy Offsite Ads (unless set above), payout fees, Payhip paid plans, Gumroad high-volume discount. Fees verified Oct 2026 — check the source links before relying on them.

Sheet Monthly Tracker
B2: MONTHLY TRACKER · log every session
B3: One row per shift/gig/sale batch. Rows 21–23 are EXAMPLE data — delete them when you start. Car cost uses the calculator's $/mile.
B5: SUMMARY | C5: This sheet | G5: Per hustle (type names) | H5: Gross | I5: Hours | J5: Take-home | K5: True hourly
B6: Gross | C6: =SUM(E21:E220) | G6: EXAMPLE: Food delivery | H6: =IF(G6="","",SUMIF($C$21:$C$220,G6,$E$21:$E$220)) | I6: =IF(G6="","",SUMIF($C$21:$C$220,G6,$F$21:$F$220)) | J6: =IF(G6="","",SUMIF($C$21:$C$220,G6,$M$21:$M$220)) | K6: =IF(OR(G6="",N(I6)=0),"",J6/I6)
B7: Hours | C7: =SUM(F21:F220) | G7: EXAMPLE: Tutoring | H7: =IF(G7="","",SUMIF($C$21:$C$220,G7,$E$21:$E$220)) | I7: =IF(G7="","",SUMIF($C$21:$C$220,G7,$F$21:$F$220)) | J7: =IF(G7="","",SUMIF($C$21:$C$220,G7,$M$21:$M$220)) | K7: =IF(OR(G7="",N(I7)=0),"",J7/I7)
B8: Net profit | C8: =SUM(K21:K220) | H8: =IF(G8="","",SUMIF($C$21:$C$220,G8,$E$21:$E$220)) | I8: =IF(G8="","",SUMIF($C$21:$C$220,G8,$F$21:$F$220)) | J8: =IF(G8="","",SUMIF($C$21:$C$220,G8,$M$21:$M$220)) | K8: =IF(OR(G8="",N(I8)=0),"",J8/I8)
B9: SE tax (approx.) | C9: =SUM(L21:L220) | H9: =IF(G9="","",SUMIF($C$21:$C$220,G9,$E$21:$E$220)) | I9: =IF(G9="","",SUMIF($C$21:$C$220,G9,$F$21:$F$220)) | J9: =IF(G9="","",SUMIF($C$21:$C$220,G9,$M$21:$M$220)) | K9: =IF(OR(G9="",N(I9)=0),"",J9/I9)
B10: Take-home | C10: =SUM(M21:M220) | H10: =IF(G10="","",SUMIF($C$21:$C$220,G10,$E$21:$E$220)) | I10: =IF(G10="","",SUMIF($C$21:$C$220,G10,$F$21:$F$220)) | J10: =IF(G10="","",SUMIF($C$21:$C$220,G10,$M$21:$M$220)) | K10: =IF(OR(G10="",N(I10)=0),"",J10/I10)
B11: TRUE HOURLY (all hustles) | C11: =IF(C7>0,C10/C7,"") | H11: =IF(G11="","",SUMIF($C$21:$C$220,G11,$E$21:$E$220)) | I11: =IF(G11="","",SUMIF($C$21:$C$220,G11,$F$21:$F$220)) | J11: =IF(G11="","",SUMIF($C$21:$C$220,G11,$M$21:$M$220)) | K11: =IF(OR(G11="",N(I11)=0),"",J11/I11)
B12: Tax set-aside % | C12: 0.25 | D12: Rule-of-thumb input, not a calculation — set your own with a tax pro.
B13: Suggested set-aside $ | C13: =MAX(0,C8)*C12
B15: Tip: lumpy months? Budget from your LOWEST recent month, not your best one — that's exactly what the FlexIncomePlanners irregular-income planners are built for.
B20: Date | C20: Hustle | D20: Platform | E20: Gross | F20: Hours | G20: Miles | H20: Fees | I20: Other exp. | J20: Car cost | K20: Net | L20: SE tax | M20: Take-home | N20: True hourly | O20: Notes
B21: 46298 | C21: EXAMPLE: Food delivery | D21: Delivery app | E21: 58.6 | F21: 4 | G21: 52 | H21: 0 | I21: 0 | J21: =IF(E21="","",N(G21)*'Hourly Pay Calculator'!$C$9) | K21: =IF(E21="","",E21-N(H21)-N(I21)-J21) | L21: =IF(E21="","",MAX(0,K21)*'Hourly Pay Calculator'!$C$13*'Hourly Pay Calculator'!$C$12) | M21: =IF(E21="","",K21-L21) | N21: =IF(OR(E21="",N(F21)=0),"",M21/F21) | O21: EXAMPLE row
B22: 46300 | C22: EXAMPLE: Tutoring | D22: Tutoring platform | E22: 80 | F22: 2.5 | G22: 0 | H22: 20 | I22: 0 | J22: =IF(E22="","",N(G22)*'Hourly Pay Calculator'!$C$9) | K22: =IF(E22="","",E22-N(H22)-N(I22)-J22) | L22: =IF(E22="","",MAX(0,K22)*'Hourly Pay Calculator'!$C$13*'Hourly Pay Calculator'!$C$12) | M22: =IF(E22="","",K22-L22) | N22: =IF(OR(E22="",N(F22)=0),"",M22/F22) | O22: EXAMPLE row (25% platform fee)
B23: 46305 | C23: EXAMPLE: Food delivery | D23: Delivery app | E23: 44 | F23: 3 | G23: 39 | H23: 0 | I23: 4 | J23: =IF(E23="","",N(G23)*'Hourly Pay Calculator'!$C$9) | K23: =IF(E23="","",E23-N(H23)-N(I23)-J23) | L23: =IF(E23="","",MAX(0,K23)*'Hourly Pay Calculator'!$C$13*'Hourly Pay Calculator'!$C$12) | M23: =IF(E23="","",K23-L23) | N23: =IF(OR(E23="",N(F23)=0),"",M23/F23) | O23: EXAMPLE row (parking $4)
J24: =IF(E24="","",N(G24)*'Hourly Pay Calculator'!$C$9) | K24: =IF(E24="","",E24-N(H24)-N(I24)-J24) | L24: =IF(E24="","",MAX(0,K24)*'Hourly Pay Calculator'!$C$13*'Hourly Pay Calculator'!$C$12) | M24: =IF(E24="","",K24-L24) | N24: =IF(OR(E24="",N(F24)=0),"",M24/F24)
J25: =IF(E25="","",N(G25)*'Hourly Pay Calculator'!$C$9) | K25: =IF(E25="","",E25-N(H25)-N(I25)-J25) | L25: =IF(E25="","",MAX(0,K25)*'Hourly Pay Calculator'!$C$13*'Hourly Pay Calculator'!$C$12) | M25: =IF(E25="","",K25-L25) | N25: =IF(OR(E25="",N(F25)=0),"",M25/F25)
J26: =IF(E26="","",N(G26)*'Hourly Pay Calculator'!$C$9) | K26: =IF(E26="","",E26-N(H26)-N(I26)-J26) | L26: =IF(E26="","",MAX(0,K26)*'Hourly Pay Calculator'!$C$13*'Hourly Pay Calculator'!$C$12) | M26: =IF(E26="","",K26-L26) | N26: =IF(OR(E26="",N(F26)=0),"",M26/F26)
J27: =IF(E27="","",N(G27)*'Hourly Pay Calculator'!$C$9) | K27: =IF(E27="","",E27-N(H27)-N(I27)-J27) | L27: =IF(E27="","",MAX(0,K27)*'Hourly Pay Calculator'!$C$13*'Hourly Pay Calculator'!$C$12) | M27: =IF(E27="","",K27-L27) | N27: =IF(OR(E27="",N(F27)=0),"",M27/F27)
J28: =IF(E28="","",N(G28)*'Hourly Pay Calculator'!$C$9) | K28: =IF(E28="","",E28-N(H28)-N(I28)-J28) | L28: =IF(E28="","",MAX(0,K28)*'Hourly Pay Calculator'!$C$13*'Hourly Pay Calculator'!$C$12) | M28: =IF(E28="","",K28-L28) | N28: =IF(OR(E28="",N(F28)=0),"",M28/F28)
J29: =IF(E29="","",N(G29)*'Hourly Pay Calculator'!$C$9) | K29: =IF(E29="","",E29-N(H29)-N(I29)-J29) | L29: =IF(E29="","",MAX(0,K29)*'Hourly Pay Calculator'!$C$13*'Hourly Pay Calculator'!$C$12) | M29: =IF(E29="","",K29-L29) | N29: =IF(OR(E29="",N(F29)=0),"",M29/F29)
J30: =IF(E30="","",N(G30)*'Hourly Pay Calculator'!$C$9) | K30: =IF(E30="","",E30-N(H30)-N(I30)-J30) | L30: =IF(E30="","",MAX(0,K30)*'Hourly Pay Calculator'!$C$13*'Hourly Pay Calculator'!$C$12) | M30: =IF(E30="","",K30-L30) | N30: =IF(OR(E30="",N(F30)=0),"",M30/F30)
J31: =IF(E31="","",N(G31)*'Hourly Pay Calculator'!$C$9) | K31: =IF(E31="","",E31-N(H31)-N(I31)-J31) | L31: =IF(E31="","",MAX(0,K31)*'Hourly Pay Calculator'!$C$13*'Hourly Pay Calculator'!$C$12) | M31: =IF(E31="","",K31-L31) | N31: =IF(OR(E31="",N(F31)=0),"",M31/F31)
J32: =IF(E32="","",N(G32)*'Hourly Pay Calculator'!$C$9) | K32: =IF(E32="","",E32-N(H32)-N(I32)-J32) | L32: =IF(E32="","",MAX(0,K32)*'Hourly Pay Calculator'!$C$13*'Hourly Pay Calculator'!$C$12) | M32: =IF(E32="","",K32-L32) | N32: =IF(OR(E32="",N(F32)=0),"",M32/F32)
J33: =IF(E33="","",N(G33)*'Hourly Pay Calculator'!$C$9) | K33: =IF(E33="","",E33-N(H33)-N(I33)-J33) | L33: =IF(E33="","",MAX(0,K33)*'Hourly Pay Calculator'!$C$13*'Hourly Pay Calculator'!$C$12) | M33: =IF(E33="","",K33-L33) | N33: =IF(OR(E33="",N(F33)=0),"",M33/F33)
J34: =IF(E34="","",N(G34)*'Hourly Pay Calculator'!$C$9) | K34: =IF(E34="","",E34-N(H34)-N(I34)-J34) | L34: =IF(E34="","",MAX(0,K34)*'Hourly Pay Calculator'!$C$13*'Hourly Pay Calculator'!$C$12) | M34: =IF(E34="","",K34-L34) | N34: =IF(OR(E34="",N(F34)=0),"",M34/F34)
J35: =IF(E35="","",N(G35)*'Hourly Pay Calculator'!$C$9) | K35: =IF(E35="","",E35-N(H35)-N(I35)-J35) | L35: =IF(E35="","",MAX(0,K35)*'Hourly Pay Calculator'!$C$13*'Hourly Pay Calculator'!$C$12) | M35: =IF(E35="","",K35-L35) | N35: =IF(OR(E35="",N(F35)=0),"",M35/F35)
... J220: =IF(E220="","",N(G220)*'Hourly Pay Calculator'!$C$9) | K220: =IF(E220="","",E220-N(H220)-N(I220)-J220) | L220: =IF(E220="","",MAX(0,K220)*'Hourly Pay Calculator'!$C$13*'Hourly Pay Calculator'!$C$12) | M220: =IF(E220="","",K220-L220) | N220: =IF(OR(E220="",N(F220)=0),"",M220/F220)
